Mathcome/__init__.py
Mathcome-3.141.dist-info/LICENSE
Mathcome-3.141.dist-info/METADATA
Mathcome-3.141.dist-info/WHEEL
Mathcome-3.141.dist-info/top_level.txt
Mathcome-3.141.dist-info/RECORD
