Metadata-Version: 2.1
Name: Mathcome
Version: 3.141
Summary: This is a project of the group Mathcome
Home-page: UNKNOWN
Author: Taebin, Yang
Author-email: ksa.yangtaebin@gmail.com
License: Mathcome
Platform: UNKNOWN
Classifier: Programming Language :: Python :: 3
